LICENSE
async_pixiv-1.1.2.dist-info/METADATA
async_pixiv-1.1.2.dist-info/WHEEL
async_pixiv-1.1.2.dist-info/entry_points.txt
async_pixiv-1.1.2.dist-info/licenses/LICENSE
async_pixiv/__init__.py
async_pixiv/client/__init__.py
async_pixiv/client/_client.py
async_pixiv/client/_client.pyi
async_pixiv/client/_net.py
async_pixiv/client/_response.py
async_pixiv/client/_transport.py
async_pixiv/client/api/__init__.py
async_pixiv/client/api/_abc.py
async_pixiv/client/api/_abc.pyi
async_pixiv/client/api/_illust.py
async_pixiv/client/api/_illust.pyi
async_pixiv/client/api/_novel.py
async_pixiv/client/api/_novel.pyi
async_pixiv/client/api/_user.py
async_pixiv/client/api/_user.pyi
async_pixiv/const.py
async_pixiv/error.py
async_pixiv/model/__init__.py
async_pixiv/model/_base.py
async_pixiv/model/illust.py
async_pixiv/model/novel.py
async_pixiv/model/other/__init__.py
async_pixiv/model/other/enums.py
async_pixiv/model/other/image.py
async_pixiv/model/other/result.py
async_pixiv/model/other/tag.py
async_pixiv/model/user.py
async_pixiv/typedefs.py
async_pixiv/utils/__init__.py
async_pixiv/utils/bypass.py
async_pixiv/utils/context.py
async_pixiv/utils/decorator.py
async_pixiv/utils/func.py
async_pixiv/utils/magic.py
async_pixiv/utils/net.py
async_pixiv/utils/overwrite.py
async_pixiv/utils/rate_limiter.py
async_pixiv/utils/singleton.py
async_pixiv/warn.py
async_pixiv-1.1.2.dist-info/RECORD
