Metadata-Version: 2.1
Name: async-pixiv
Version: 1.1.2
Summary: Async Pixiv API for Python.
Keywords: pixiv,async,pixiv-api
Author-Email: Arko <arko.space.cc@gmail.com>, Karako <karako@karako.moe>
Maintainer-Email: Karako <karako@karako.moe>
License: MIT
Classifier: License :: OSI Approved :: MIT License
Classifier: Programming Language :: Python :: 3 :: Only
Classifier: Programming Language :: Python :: 3.12
Classifier: Programming Language :: Python :: 3.13
Classifier: Programming Language :: Python :: Implementation :: CPython
Classifier: Topic :: Software Development :: Libraries :: Python Modules
Project-URL: homepage, https://github.com/ArkoClub/async-pixiv
Project-URL: repository, https://github.com/ArkoClub/async-pixiv
Requires-Python: >=3.12
Requires-Dist: pydantic[email]>=2.5.3
Requires-Dist: aiofiles>=24.1.0
Requires-Dist: httpx>=0.27.0
Requires-Dist: aiohttp-socks>=0.9.0
Requires-Dist: msgspec>=0.18.0
Requires-Dist: aiolimiter>=1.1.0
Requires-Dist: requests>=2.32.0
Requires-Dist: python-ffmpeg<3.0.0,>=2.0.12
Requires-Dist: pytz>=2024.2
Requires-Dist: tzlocal>=5.2
Provides-Extra: speedups
Requires-Dist: regex; extra == "speedups"
Requires-Dist: orjson; extra == "speedups"
Requires-Dist: uvloop<1.0.0,>=0.16.0; sys_platform != "win32" and extra == "speedups"
Provides-Extra: dev
Requires-Dist: pytest<9.0,>=8.0; extra == "dev"
Requires-Dist: black; extra == "dev"
Requires-Dist: pytest-asyncio<0.24.0,>=0.23.5; extra == "dev"
Requires-Dist: pytest-env>=1.1.3; extra == "dev"
